diddy_doo_dad/__init__.py
diddy_doo_dad/main.py
diddy_doo_dad-0.0.4.dist-info/LICENSE
diddy_doo_dad-0.0.4.dist-info/METADATA
diddy_doo_dad-0.0.4.dist-info/WHEEL
diddy_doo_dad-0.0.4.dist-info/top_level.txt
diddy_doo_dad-0.0.4.dist-info/RECORD
