Metadata-Version: 2.1
Name: diddy-doo-dad
Version: 0.0.4
Summary: Just a project for learning this process.
Home-page: https://github.com/pypa/sampleproject
Author: Matt Bockman
Author-email: mattbockman@gmail.com
Project-URL: Bug Tracker, https://github.com/pypa/sampleproject/issues
Classifier: Programming Language :: Python :: 3
Classifier: License :: OSI Approved :: MIT License
Classifier: Operating System :: OS Independent
Requires-Python: >=3.6
License-File: LICENSE
Requires-Dist: rich
